KeiLib/__init__.py
KeiLib/args.py
KeiLib/config.py
KeiLib/wrapper.py
KeiLib/users_manager/__init__.py
KeiLib/users_manager/campus_users.py
KeiLib/users_manager/student_details.py
KeiLib-0.0.4.dist-info/LICENSE
KeiLib-0.0.4.dist-info/METADATA
KeiLib-0.0.4.dist-info/WHEEL
KeiLib-0.0.4.dist-info/top_level.txt
KeiLib-0.0.4.dist-info/RECORD
