Metadata-Version: 2.1
Name: KeiLib
Version: 0.0.4
Summary: My personal library for using 42API.
Home-page: https://gitlab.com/kei0x/keilib
Author: Kei0x
Author-email: kei0x@protonmail.com
License: UNKNOWN
Platform: UNKNOWN
Classifier: Programming Language :: Python :: 3
Classifier: Operating System :: OS Independent
Requires-Python: >=3.6
